feapder/VERSION
feapder/__init__.py
feapder/requirements.txt
feapder/setting.py
feapder/buffer/__init__.py
feapder/buffer/item_buffer.py
feapder/buffer/request_buffer.py
feapder/commands/__init__.py
feapder/commands/cmdline.py
feapder/commands/create_builder.py
feapder/commands/retry.py
feapder/commands/shell.py
feapder/commands/zip.py
feapder/commands/create/__init__.py
feapder/commands/create/create_cookies.py
feapder/commands/create/create_init.py
feapder/commands/create/create_item.py
feapder/commands/create/create_json.py
feapder/commands/create/create_params.py
feapder/commands/create/create_project.py
feapder/commands/create/create_setting.py
feapder/commands/create/create_spider.py
feapder/commands/create/create_table.py
feapder/core/__init__.py
feapder/core/base_parser.py
feapder/core/collector.py
feapder/core/handle_failed_items.py
feapder/core/handle_failed_requests.py
feapder/core/parser_control.py
feapder/core/scheduler.py
feapder/core/spiders/__init__.py
feapder/core/spiders/air_spider.py
feapder/core/spiders/batch_spider.py
feapder/core/spiders/spider.py
feapder/core/spiders/task_spider.py
feapder/db/__init__.py
feapder/db/memorydb.py
feapder/db/mongodb.py
feapder/db/mysqldb.py
feapder/db/redisdb.py
feapder/dedup/__init__.py
feapder/dedup/basefilter.py
feapder/dedup/bitarray.py
feapder/dedup/bloomfilter.py
feapder/dedup/expirefilter.py
feapder/dedup/litefilter.py
feapder/network/__init__.py
feapder/network/item.py
feapder/network/proxy_pool_old.py
feapder/network/request.py
feapder/network/response.py
feapder/network/selector.py
feapder/network/user_agent.py
feapder/network/downloader/__init__.py
feapder/network/downloader/_playwright.py
feapder/network/downloader/_requests.py
feapder/network/downloader/_selenium.py
feapder/network/downloader/base.py
feapder/network/proxy_pool/__init__.py
feapder/network/proxy_pool/base.py
feapder/network/proxy_pool/proxy_pool.py
feapder/network/user_pool/__init__.py
feapder/network/user_pool/base_user_pool.py
feapder-1.9.3.dist-info/LICENSE
feapder-1.9.3.dist-info/METADATA
feapder-1.9.3.dist-info/WHEEL
feapder-1.9.3.dist-info/entry_points.txt
feapder-1.9.3.dist-info/top_level.txt
feapder-1.9.3.dist-info/RECORD
